musa_deploy/README.md
musa_deploy/__init__.py
musa_deploy/auto_gen.py
musa_deploy/main.py
musa_deploy/utils.py
musa_deploy/__pycache__/__init__.cpython-38.pyc
musa_deploy/ansible/__init__.py
musa_deploy/ansible/inventory_examples.yaml
musa_deploy/ansible/main.py
musa_deploy/ansible/playbook/init_docker_swarm_playbook.yaml
musa_deploy/ansible/playbook/playbook_template.yaml
musa_deploy/ansible/playbook/reset_docker_swarm_playbook.yaml
musa_deploy/ansible/playbook/start_service_playbook.yaml
musa_deploy/ansible/playbook/roles/check_and_deny_deploy_demo/tasks/main.yml
musa_deploy/ansible/playbook/roles/check_and_deny_deploy_demo/vars/main.yml
musa_deploy/ansible/service/stack_template.yaml
musa_deploy/ansible/shell/run_deepseek_671b_r1.sh
musa_deploy/check/README.md
musa_deploy/check/__init__.py
musa_deploy/check/checker.py
musa_deploy/check/diagnoser.py
musa_deploy/check/shell_executor.py
musa_deploy/check/utils.py
musa_deploy/check/test/test_musa.mu
musa_deploy/check/test/torch_demo.py
musa_deploy/check/test/torch_musa_demo.py
musa_deploy/check/test/torchaudio_demo.py
musa_deploy/check/test/torchvision_demo.py
musa_deploy/check/test/vllm_demo.py
musa_deploy/config/version_requirements.yaml
musa_deploy/config/yaml_read.py
musa_deploy/config/download/driver.yaml
musa_deploy/config/download/kuae_sdk.yaml
musa_deploy/config/download/mccl.yaml
musa_deploy/config/download/mt-container-toolkit.yaml
musa_deploy/config/download/mtml.yaml
musa_deploy/config/download/mudnn.yaml
musa_deploy/config/download/musa_toolkits.yaml
musa_deploy/config/download/sdk.yaml
musa_deploy/config/download/sgpu-dkms.yaml
musa_deploy/config/download/smartio.yaml
musa_deploy/config/download/torch_musa.yaml
musa_deploy/config/download/images/torch_musa_images.yaml
musa_deploy/config/download/images/ubuntu_images.yaml
musa_deploy/config/download/images/vllm_images.yaml
musa_deploy/demo/__init__.py
musa_deploy/demo/demo.py
musa_deploy/demo/utils.py
musa_deploy/download/__init__.py
musa_deploy-0.7.0.dist-info/METADATA
musa_deploy-0.7.0.dist-info/WHEEL
musa_deploy-0.7.0.dist-info/entry_points.txt
musa_deploy-0.7.0.dist-info/top_level.txt
musa_deploy-0.7.0.dist-info/RECORD
