Metadata-Version: 2.1
Name: musa-deploy
Version: 0.7.0
Summary: musa environment deployment tool
Home-page: UNKNOWN
Author: Moore Threads GPU Genius Team
License: Apache
Platform: UNKNOWN
Requires-Python: >= 3.6
Requires-Dist: ansible (==6.7.0)
Requires-Dist: distro (==1.9.0)
Requires-Dist: pexpect (==4.9.0)
Requires-Dist: psutil (==7.0.0)
Requires-Dist: py-cpuinfo (==9.0.0)
Requires-Dist: pyyaml (==6.0.2)
Requires-Dist: requests (==2.32.3)
Requires-Dist: ruamel.yaml.clib (==0.2.8)
Requires-Dist: ruamel.yaml (==0.18.10)
Requires-Dist: tqdm (==4.67.1)
